setup.cfg
setup.py
quicklog/__init__.py
quicklog/quicklog.py
quicklog.egg-info/PKG-INFO
quicklog.egg-info/SOURCES.txt
quicklog.egg-info/dependency_links.txt
quicklog.egg-info/top_level.txt