Metadata-Version: 1.1
Name: quicklog
Version: 1.1.1
Summary: Small logging utility
Home-page: http://packages.python.org/QuickLog
Author: Chris Anoikesis
Author-email: tutow@hotmail.com
License: MIT
Keywords: logging
Platform: UNKNOWN
Classifier: License :: OSI Approved :: MIT License
Classifier: Programming Language :: Python :: 2 :: Only
Classifier: Development Status :: 4 - Beta
Classifier: Intended Audience :: Developers
Classifier: Topic :: Utilities
